{
  "elements": [
    {
      "type": "element",
      "name": "group",
      "elements": [
        {
          "type": "element",
          "name": "opcode",
          "attributes": {
            "name": "volume",
            "value": "-6.5"
          }
        },
        {
          "type": "element",
          "name": "opcode",
          "attributes": {
            "name": "ampeg_attackcc1",
            "value": "0.5"
          }
        },
        {
          "type": "element",
          "name": "opcode",
          "attributes": {
            "name": "gain_cc1",
            "value": "-15"
          }
        },
        {
          "type": "element",
          "name": "opcode",
          "attributes": {
            "name": "pitch_random",
            "value": "12"
          }
        },
        {
          "type": "element",
          "name": "opcode",
          "attributes": {
            "name": "amp_random",
            "value": "1.5"
          }
        },
        {
          "type": "element",
          "name": "opcode",
          "attributes": {
            "name": "delay_random",
            "value": "0.012"
          }
        },
        {
          "type": "element",
          "name": "opcode",
          "attributes": {
            "name": "loop_mode",
            "value": "one_shot"
          }
        },
        {
          "type": "element",
          "name": "opcode",
          "attributes": {
            "name": "seq_position",
            "value": "1"
          }
        },
        {
          "type": "element",
          "name": "opcode",
          "attributes": {
            "name": "seq_length",
            "value": "2"
          }
        },
        {
          "type": "element",
          "name": "opcode",
          "attributes": {
            "name": "tune",
            "value": "4"
          }
        },
        {
          "type": "element",
          "name": "opcode",
          "attributes": {
            "name": "ampeg_sustain",
            "value": "0"
          }
        },
        {
          "type": "element",
          "name": "opcode",
          "attributes": {
            "name": "ampeg_decay",
            "value": "1"
          }
        },
        {
          "type": "element",
          "name": "opcode",
          "attributes": {
            "name": "ampeg_vel2decay",
            "value": "10"
          }
        }
      ]
    },
    {
      "type": "element",
      "name": "region",
      "elements": [
        {
          "type": "element",
          "name": "opcode",
          "attributes": {
            "name": "sample",
            "value": "..\\libs\\SSO\\Samples\\1st Violins\\1st-violins-stc-rr1-g3-PB.ogg"
          }
        },
        {
          "type": "element",
          "name": "opcode",
          "attributes": {
            "name": "volume",
            "value": "-2"
          }
        },
        {
          "type": "element",
          "name": "opcode",
          "attributes": {
            "name": "lokey",
            "value": "g3"
          }
        },
        {
          "type": "element",
          "name": "opcode",
          "attributes": {
            "name": "hikey",
            "value": "g#3"
          }
        },
        {
          "type": "element",
          "name": "opcode",
          "attributes": {
            "name": "pitch_keycenter",
            "value": "g3"
          }
        }
      ]
    },
    {
      "type": "element",
      "name": "region",
      "elements": [
        {
          "type": "element",
          "name": "opcode",
          "attributes": {
            "name": "sample",
            "value": "..\\libs\\SSO\\Samples\\1st Violins\\1st-violins-stc-rr1-a#3-PB.ogg"
          }
        },
        {
          "type": "element",
          "name": "opcode",
          "attributes": {
            "name": "volume",
            "value": "-2.5"
          }
        },
        {
          "type": "element",
          "name": "opcode",
          "attributes": {
            "name": "lokey",
            "value": "a3"
          }
        },
        {
          "type": "element",
          "name": "opcode",
          "attributes": {
            "name": "hikey",
            "value": "b3"
          }
        },
        {
          "type": "element",
          "name": "opcode",
          "attributes": {
            "name": "pitch_keycenter",
            "value": "a#3"
          }
        }
      ]
    },
    {
      "type": "element",
      "name": "region",
      "elements": [
        {
          "type": "element",
          "name": "opcode",
          "attributes": {
            "name": "sample",
            "value": "..\\libs\\SSO\\Samples\\1st Violins\\1st-violins-stc-rr1-c#4-PB.ogg"
          }
        },
        {
          "type": "element",
          "name": "opcode",
          "attributes": {
            "name": "volume",
            "value": "-2.5"
          }
        },
        {
          "type": "element",
          "name": "opcode",
          "attributes": {
            "name": "lokey",
            "value": "c4"
          }
        },
        {
          "type": "element",
          "name": "opcode",
          "attributes": {
            "name": "hikey",
            "value": "d4"
          }
        },
        {
          "type": "element",
          "name": "opcode",
          "attributes": {
            "name": "pitch_keycenter",
            "value": "c#4"
          }
        }
      ]
    },
    {
      "type": "element",
      "name": "region",
      "elements": [
        {
          "type": "element",
          "name": "opcode",
          "attributes": {
            "name": "sample",
            "value": "..\\libs\\SSO\\Samples\\1st Violins\\1st-violins-stc-rr1-e4-PB.ogg"
          }
        },
        {
          "type": "element",
          "name": "opcode",
          "attributes": {
            "name": "volume",
            "value": "-0.5"
          }
        },
        {
          "type": "element",
          "name": "opcode",
          "attributes": {
            "name": "lokey",
            "value": "d#4"
          }
        },
        {
          "type": "element",
          "name": "opcode",
          "attributes": {
            "name": "hikey",
            "value": "f4"
          }
        },
        {
          "type": "element",
          "name": "opcode",
          "attributes": {
            "name": "pitch_keycenter",
            "value": "e4"
          }
        }
      ]
    },
    {
      "type": "element",
      "name": "region",
      "elements": [
        {
          "type": "element",
          "name": "opcode",
          "attributes": {
            "name": "sample",
            "value": "..\\libs\\SSO\\Samples\\1st Violins\\1st-violins-stc-rr1-g4-PB.ogg"
          }
        },
        {
          "type": "element",
          "name": "opcode",
          "attributes": {
            "name": "volume",
            "value": "-3.5"
          }
        },
        {
          "type": "element",
          "name": "opcode",
          "attributes": {
            "name": "lokey",
            "value": "f#4"
          }
        },
        {
          "type": "element",
          "name": "opcode",
          "attributes": {
            "name": "hikey",
            "value": "g#4"
          }
        },
        {
          "type": "element",
          "name": "opcode",
          "attributes": {
            "name": "pitch_keycenter",
            "value": "g4"
          }
        }
      ]
    },
    {
      "type": "element",
      "name": "region",
      "elements": [
        {
          "type": "element",
          "name": "opcode",
          "attributes": {
            "name": "sample",
            "value": "..\\libs\\SSO\\Samples\\1st Violins\\1st-violins-stc-rr1-a#4-PB.ogg"
          }
        },
        {
          "type": "element",
          "name": "opcode",
          "attributes": {
            "name": "volume",
            "value": "-1.5"
          }
        },
        {
          "type": "element",
          "name": "opcode",
          "attributes": {
            "name": "lokey",
            "value": "a4"
          }
        },
        {
          "type": "element",
          "name": "opcode",
          "attributes": {
            "name": "hikey",
            "value": "b4"
          }
        },
        {
          "type": "element",
          "name": "opcode",
          "attributes": {
            "name": "pitch_keycenter",
            "value": "a#4"
          }
        }
      ]
    },
    {
      "type": "element",
      "name": "region",
      "elements": [
        {
          "type": "element",
          "name": "opcode",
          "attributes": {
            "name": "sample",
            "value": "..\\libs\\SSO\\Samples\\1st Violins\\1st-violins-stc-rr1-c#5-PB.ogg"
          }
        },
        {
          "type": "element",
          "name": "opcode",
          "attributes": {
            "name": "volume",
            "value": "-2.5"
          }
        },
        {
          "type": "element",
          "name": "opcode",
          "attributes": {
            "name": "lokey",
            "value": "c5"
          }
        },
        {
          "type": "element",
          "name": "opcode",
          "attributes": {
            "name": "hikey",
            "value": "d5"
          }
        },
        {
          "type": "element",
          "name": "opcode",
          "attributes": {
            "name": "pitch_keycenter",
            "value": "c#5"
          }
        }
      ]
    },
    {
      "type": "element",
      "name": "region",
      "elements": [
        {
          "type": "element",
          "name": "opcode",
          "attributes": {
            "name": "sample",
            "value": "..\\libs\\SSO\\Samples\\1st Violins\\1st-violins-stc-rr1-e5-PB.ogg"
          }
        },
        {
          "type": "element",
          "name": "opcode",
          "attributes": {
            "name": "volume",
            "value": "-3.5"
          }
        },
        {
          "type": "element",
          "name": "opcode",
          "attributes": {
            "name": "lokey",
            "value": "d#5"
          }
        },
        {
          "type": "element",
          "name": "opcode",
          "attributes": {
            "name": "hikey",
            "value": "f5"
          }
        },
        {
          "type": "element",
          "name": "opcode",
          "attributes": {
            "name": "pitch_keycenter",
            "value": "e5"
          }
        }
      ]
    },
    {
      "type": "element",
      "name": "region",
      "elements": [
        {
          "type": "element",
          "name": "opcode",
          "attributes": {
            "name": "sample",
            "value": "..\\libs\\SSO\\Samples\\1st Violins\\1st-violins-stc-rr1-g5-PB.ogg"
          }
        },
        {
          "type": "element",
          "name": "opcode",
          "attributes": {
            "name": "volume",
            "value": "-1.5"
          }
        },
        {
          "type": "element",
          "name": "opcode",
          "attributes": {
            "name": "lokey",
            "value": "f#5"
          }
        },
        {
          "type": "element",
          "name": "opcode",
          "attributes": {
            "name": "hikey",
            "value": "g#5"
          }
        },
        {
          "type": "element",
          "name": "opcode",
          "attributes": {
            "name": "pitch_keycenter",
            "value": "g5"
          }
        }
      ]
    },
    {
      "type": "element",
      "name": "region",
      "elements": [
        {
          "type": "element",
          "name": "opcode",
          "attributes": {
            "name": "sample",
            "value": "..\\libs\\SSO\\Samples\\1st Violins\\1st-violins-stc-rr1-a#5-PB.ogg"
          }
        },
        {
          "type": "element",
          "name": "opcode",
          "attributes": {
            "name": "volume",
            "value": "1.5"
          }
        },
        {
          "type": "element",
          "name": "opcode",
          "attributes": {
            "name": "lokey",
            "value": "a5"
          }
        },
        {
          "type": "element",
          "name": "opcode",
          "attributes": {
            "name": "hikey",
            "value": "b5"
          }
        },
        {
          "type": "element",
          "name": "opcode",
          "attributes": {
            "name": "pitch_keycenter",
            "value": "a#5"
          }
        }
      ]
    },
    {
      "type": "element",
      "name": "region",
      "elements": [
        {
          "type": "element",
          "name": "opcode",
          "attributes": {
            "name": "sample",
            "value": "..\\libs\\SSO\\Samples\\1st Violins\\1st-violins-stc-rr1-c#6-PB.ogg"
          }
        },
        {
          "type": "element",
          "name": "opcode",
          "attributes": {
            "name": "volume",
            "value": "-1.5"
          }
        },
        {
          "type": "element",
          "name": "opcode",
          "attributes": {
            "name": "lokey",
            "value": "c6"
          }
        },
        {
          "type": "element",
          "name": "opcode",
          "attributes": {
            "name": "hikey",
            "value": "d6"
          }
        },
        {
          "type": "element",
          "name": "opcode",
          "attributes": {
            "name": "pitch_keycenter",
            "value": "c#6"
          }
        }
      ]
    },
    {
      "type": "element",
      "name": "region",
      "elements": [
        {
          "type": "element",
          "name": "opcode",
          "attributes": {
            "name": "sample",
            "value": "..\\libs\\SSO\\Samples\\1st Violins\\1st-violins-stc-rr1-e6-PB.ogg"
          }
        },
        {
          "type": "element",
          "name": "opcode",
          "attributes": {
            "name": "volume",
            "value": "-2.5"
          }
        },
        {
          "type": "element",
          "name": "opcode",
          "attributes": {
            "name": "lokey",
            "value": "d#6"
          }
        },
        {
          "type": "element",
          "name": "opcode",
          "attributes": {
            "name": "hikey",
            "value": "f6"
          }
        },
        {
          "type": "element",
          "name": "opcode",
          "attributes": {
            "name": "pitch_keycenter",
            "value": "e6"
          }
        }
      ]
    },
    {
      "type": "element",
      "name": "region",
      "elements": [
        {
          "type": "element",
          "name": "opcode",
          "attributes": {
            "name": "sample",
            "value": "..\\libs\\SSO\\Samples\\1st Violins\\1st-violins-stc-rr1-g6-PB.ogg"
          }
        },
        {
          "type": "element",
          "name": "opcode",
          "attributes": {
            "name": "volume",
            "value": "-3.5"
          }
        },
        {
          "type": "element",
          "name": "opcode",
          "attributes": {
            "name": "lokey",
            "value": "f#6"
          }
        },
        {
          "type": "element",
          "name": "opcode",
          "attributes": {
            "name": "hikey",
            "value": "g#6"
          }
        },
        {
          "type": "element",
          "name": "opcode",
          "attributes": {
            "name": "pitch_keycenter",
            "value": "g6"
          }
        }
      ]
    },
    {
      "type": "element",
      "name": "region",
      "elements": [
        {
          "type": "element",
          "name": "opcode",
          "attributes": {
            "name": "sample",
            "value": "..\\libs\\SSO\\Samples\\1st Violins\\1st-violins-stc-rr1-a#6-PB.ogg"
          }
        },
        {
          "type": "element",
          "name": "opcode",
          "attributes": {
            "name": "volume",
            "value": "-3.5"
          }
        },
        {
          "type": "element",
          "name": "opcode",
          "attributes": {
            "name": "lokey",
            "value": "a6"
          }
        },
        {
          "type": "element",
          "name": "opcode",
          "attributes": {
            "name": "hikey",
            "value": "a7"
          }
        },
        {
          "type": "element",
          "name": "opcode",
          "attributes": {
            "name": "pitch_keycenter",
            "value": "a#6"
          }
        }
      ]
    },
    {
      "type": "element",
      "name": "group",
      "elements": [
        {
          "type": "element",
          "name": "opcode",
          "attributes": {
            "name": "volume",
            "value": "-6.5"
          }
        },
        {
          "type": "element",
          "name": "opcode",
          "attributes": {
            "name": "ampeg_attackcc1",
            "value": "0.5"
          }
        },
        {
          "type": "element",
          "name": "opcode",
          "attributes": {
            "name": "gain_cc1",
            "value": "-15"
          }
        },
        {
          "type": "element",
          "name": "opcode",
          "attributes": {
            "name": "pitch_random",
            "value": "12"
          }
        },
        {
          "type": "element",
          "name": "opcode",
          "attributes": {
            "name": "amp_random",
            "value": "1.5"
          }
        },
        {
          "type": "element",
          "name": "opcode",
          "attributes": {
            "name": "delay_random",
            "value": "0.012"
          }
        },
        {
          "type": "element",
          "name": "opcode",
          "attributes": {
            "name": "loop_mode",
            "value": "one_shot"
          }
        },
        {
          "type": "element",
          "name": "opcode",
          "attributes": {
            "name": "seq_position",
            "value": "2"
          }
        },
        {
          "type": "element",
          "name": "opcode",
          "attributes": {
            "name": "seq_length",
            "value": "2"
          }
        },
        {
          "type": "element",
          "name": "opcode",
          "attributes": {
            "name": "transpose",
            "value": "-1"
          }
        },
        {
          "type": "element",
          "name": "opcode",
          "attributes": {
            "name": "ampeg_sustain",
            "value": "0"
          }
        },
        {
          "type": "element",
          "name": "opcode",
          "attributes": {
            "name": "ampeg_decay",
            "value": "1"
          }
        },
        {
          "type": "element",
          "name": "opcode",
          "attributes": {
            "name": "ampeg_vel2decay",
            "value": "10"
          }
        }
      ]
    },
    {
      "type": "element",
      "name": "region",
      "elements": [
        {
          "type": "element",
          "name": "opcode",
          "attributes": {
            "name": "sample",
            "value": "..\\libs\\SSO\\Samples\\1st Violins\\1st-violins-stc-rr2-g3-PB.ogg"
          }
        },
        {
          "type": "element",
          "name": "opcode",
          "attributes": {
            "name": "volume",
            "value": "-2.5"
          }
        },
        {
          "type": "element",
          "name": "opcode",
          "attributes": {
            "name": "lokey",
            "value": "g3"
          }
        },
        {
          "type": "element",
          "name": "opcode",
          "attributes": {
            "name": "hikey",
            "value": "g#3"
          }
        },
        {
          "type": "element",
          "name": "opcode",
          "attributes": {
            "name": "pitch_keycenter",
            "value": "g3"
          }
        }
      ]
    },
    {
      "type": "element",
      "name": "region",
      "elements": [
        {
          "type": "element",
          "name": "opcode",
          "attributes": {
            "name": "sample",
            "value": "..\\libs\\SSO\\Samples\\1st Violins\\1st-violins-stc-rr2-a#3-PB.ogg"
          }
        },
        {
          "type": "element",
          "name": "opcode",
          "attributes": {
            "name": "volume",
            "value": "-2.5"
          }
        },
        {
          "type": "element",
          "name": "opcode",
          "attributes": {
            "name": "lokey",
            "value": "a3"
          }
        },
        {
          "type": "element",
          "name": "opcode",
          "attributes": {
            "name": "hikey",
            "value": "b3"
          }
        },
        {
          "type": "element",
          "name": "opcode",
          "attributes": {
            "name": "pitch_keycenter",
            "value": "a#3"
          }
        }
      ]
    },
    {
      "type": "element",
      "name": "region",
      "elements": [
        {
          "type": "element",
          "name": "opcode",
          "attributes": {
            "name": "sample",
            "value": "..\\libs\\SSO\\Samples\\1st Violins\\1st-violins-stc-rr2-c#4-PB.ogg"
          }
        },
        {
          "type": "element",
          "name": "opcode",
          "attributes": {
            "name": "volume",
            "value": "-2.5"
          }
        },
        {
          "type": "element",
          "name": "opcode",
          "attributes": {
            "name": "lokey",
            "value": "c4"
          }
        },
        {
          "type": "element",
          "name": "opcode",
          "attributes": {
            "name": "hikey",
            "value": "d4"
          }
        },
        {
          "type": "element",
          "name": "opcode",
          "attributes": {
            "name": "pitch_keycenter",
            "value": "c#4"
          }
        }
      ]
    },
    {
      "type": "element",
      "name": "region",
      "elements": [
        {
          "type": "element",
          "name": "opcode",
          "attributes": {
            "name": "sample",
            "value": "..\\libs\\SSO\\Samples\\1st Violins\\1st-violins-stc-rr2-e4-PB.ogg"
          }
        },
        {
          "type": "element",
          "name": "opcode",
          "attributes": {
            "name": "volume",
            "value": "-1.5"
          }
        },
        {
          "type": "element",
          "name": "opcode",
          "attributes": {
            "name": "lokey",
            "value": "d#4"
          }
        },
        {
          "type": "element",
          "name": "opcode",
          "attributes": {
            "name": "hikey",
            "value": "f4"
          }
        },
        {
          "type": "element",
          "name": "opcode",
          "attributes": {
            "name": "pitch_keycenter",
            "value": "e4"
          }
        }
      ]
    },
    {
      "type": "element",
      "name": "region",
      "elements": [
        {
          "type": "element",
          "name": "opcode",
          "attributes": {
            "name": "sample",
            "value": "..\\libs\\SSO\\Samples\\1st Violins\\1st-violins-stc-rr2-g4-PB.ogg"
          }
        },
        {
          "type": "element",
          "name": "opcode",
          "attributes": {
            "name": "volume",
            "value": "-3.5"
          }
        },
        {
          "type": "element",
          "name": "opcode",
          "attributes": {
            "name": "lokey",
            "value": "f#4"
          }
        },
        {
          "type": "element",
          "name": "opcode",
          "attributes": {
            "name": "hikey",
            "value": "g#4"
          }
        },
        {
          "type": "element",
          "name": "opcode",
          "attributes": {
            "name": "pitch_keycenter",
            "value": "g4"
          }
        }
      ]
    },
    {
      "type": "element",
      "name": "region",
      "elements": [
        {
          "type": "element",
          "name": "opcode",
          "attributes": {
            "name": "sample",
            "value": "..\\libs\\SSO\\Samples\\1st Violins\\1st-violins-stc-rr2-a#4-PB.ogg"
          }
        },
        {
          "type": "element",
          "name": "opcode",
          "attributes": {
            "name": "volume",
            "value": "-3.5"
          }
        },
        {
          "type": "element",
          "name": "opcode",
          "attributes": {
            "name": "lokey",
            "value": "a4"
          }
        },
        {
          "type": "element",
          "name": "opcode",
          "attributes": {
            "name": "hikey",
            "value": "b4"
          }
        },
        {
          "type": "element",
          "name": "opcode",
          "attributes": {
            "name": "pitch_keycenter",
            "value": "a#4"
          }
        }
      ]
    },
    {
      "type": "element",
      "name": "region",
      "elements": [
        {
          "type": "element",
          "name": "opcode",
          "attributes": {
            "name": "sample",
            "value": "..\\libs\\SSO\\Samples\\1st Violins\\1st-violins-stc-rr2-c#5-PB.ogg"
          }
        },
        {
          "type": "element",
          "name": "opcode",
          "attributes": {
            "name": "volume",
            "value": "-1.5"
          }
        },
        {
          "type": "element",
          "name": "opcode",
          "attributes": {
            "name": "lokey",
            "value": "c5"
          }
        },
        {
          "type": "element",
          "name": "opcode",
          "attributes": {
            "name": "hikey",
            "value": "d5"
          }
        },
        {
          "type": "element",
          "name": "opcode",
          "attributes": {
            "name": "pitch_keycenter",
            "value": "c#5"
          }
        }
      ]
    },
    {
      "type": "element",
      "name": "region",
      "elements": [
        {
          "type": "element",
          "name": "opcode",
          "attributes": {
            "name": "sample",
            "value": "..\\libs\\SSO\\Samples\\1st Violins\\1st-violins-stc-rr2-e5-PB.ogg"
          }
        },
        {
          "type": "element",
          "name": "opcode",
          "attributes": {
            "name": "volume",
            "value": "-2.5"
          }
        },
        {
          "type": "element",
          "name": "opcode",
          "attributes": {
            "name": "lokey",
            "value": "d#5"
          }
        },
        {
          "type": "element",
          "name": "opcode",
          "attributes": {
            "name": "hikey",
            "value": "f5"
          }
        },
        {
          "type": "element",
          "name": "opcode",
          "attributes": {
            "name": "pitch_keycenter",
            "value": "e5"
          }
        }
      ]
    },
    {
      "type": "element",
      "name": "region",
      "elements": [
        {
          "type": "element",
          "name": "opcode",
          "attributes": {
            "name": "sample",
            "value": "..\\libs\\SSO\\Samples\\1st Violins\\1st-violins-stc-rr2-g5-PB.ogg"
          }
        },
        {
          "type": "element",
          "name": "opcode",
          "attributes": {
            "name": "volume",
            "value": "-0.5"
          }
        },
        {
          "type": "element",
          "name": "opcode",
          "attributes": {
            "name": "lokey",
            "value": "f#5"
          }
        },
        {
          "type": "element",
          "name": "opcode",
          "attributes": {
            "name": "hikey",
            "value": "g#5"
          }
        },
        {
          "type": "element",
          "name": "opcode",
          "attributes": {
            "name": "pitch_keycenter",
            "value": "g5"
          }
        }
      ]
    },
    {
      "type": "element",
      "name": "region",
      "elements": [
        {
          "type": "element",
          "name": "opcode",
          "attributes": {
            "name": "sample",
            "value": "..\\libs\\SSO\\Samples\\1st Violins\\1st-violins-stc-rr2-a#5-PB.ogg"
          }
        },
        {
          "type": "element",
          "name": "opcode",
          "attributes": {
            "name": "volume",
            "value": "-0.5"
          }
        },
        {
          "type": "element",
          "name": "opcode",
          "attributes": {
            "name": "lokey",
            "value": "a5"
          }
        },
        {
          "type": "element",
          "name": "opcode",
          "attributes": {
            "name": "hikey",
            "value": "b5"
          }
        },
        {
          "type": "element",
          "name": "opcode",
          "attributes": {
            "name": "pitch_keycenter",
            "value": "a#5"
          }
        }
      ]
    },
    {
      "type": "element",
      "name": "region",
      "elements": [
        {
          "type": "element",
          "name": "opcode",
          "attributes": {
            "name": "sample",
            "value": "..\\libs\\SSO\\Samples\\1st Violins\\1st-violins-stc-rr2-c#6-PB.ogg"
          }
        },
        {
          "type": "element",
          "name": "opcode",
          "attributes": {
            "name": "volume",
            "value": "-1.5"
          }
        },
        {
          "type": "element",
          "name": "opcode",
          "attributes": {
            "name": "lokey",
            "value": "c6"
          }
        },
        {
          "type": "element",
          "name": "opcode",
          "attributes": {
            "name": "hikey",
            "value": "d6"
          }
        },
        {
          "type": "element",
          "name": "opcode",
          "attributes": {
            "name": "pitch_keycenter",
            "value": "c#6"
          }
        }
      ]
    },
    {
      "type": "element",
      "name": "region",
      "elements": [
        {
          "type": "element",
          "name": "opcode",
          "attributes": {
            "name": "sample",
            "value": "..\\libs\\SSO\\Samples\\1st Violins\\1st-violins-stc-rr2-e6-PB.ogg"
          }
        },
        {
          "type": "element",
          "name": "opcode",
          "attributes": {
            "name": "volume",
            "value": "-3.5"
          }
        },
        {
          "type": "element",
          "name": "opcode",
          "attributes": {
            "name": "lokey",
            "value": "d#6"
          }
        },
        {
          "type": "element",
          "name": "opcode",
          "attributes": {
            "name": "hikey",
            "value": "f6"
          }
        },
        {
          "type": "element",
          "name": "opcode",
          "attributes": {
            "name": "pitch_keycenter",
            "value": "e6"
          }
        }
      ]
    },
    {
      "type": "element",
      "name": "region",
      "elements": [
        {
          "type": "element",
          "name": "opcode",
          "attributes": {
            "name": "sample",
            "value": "..\\libs\\SSO\\Samples\\1st Violins\\1st-violins-stc-rr2-g6-PB.ogg"
          }
        },
        {
          "type": "element",
          "name": "opcode",
          "attributes": {
            "name": "volume",
            "value": "-2.5"
          }
        },
        {
          "type": "element",
          "name": "opcode",
          "attributes": {
            "name": "lokey",
            "value": "f#6"
          }
        },
        {
          "type": "element",
          "name": "opcode",
          "attributes": {
            "name": "hikey",
            "value": "g#6"
          }
        },
        {
          "type": "element",
          "name": "opcode",
          "attributes": {
            "name": "pitch_keycenter",
            "value": "g6"
          }
        }
      ]
    },
    {
      "type": "element",
      "name": "region",
      "elements": [
        {
          "type": "element",
          "name": "opcode",
          "attributes": {
            "name": "sample",
            "value": "..\\libs\\SSO\\Samples\\1st Violins\\1st-violins-stc-rr2-a#6-PB.ogg"
          }
        },
        {
          "type": "element",
          "name": "opcode",
          "attributes": {
            "name": "volume",
            "value": "-3.5"
          }
        },
        {
          "type": "element",
          "name": "opcode",
          "attributes": {
            "name": "lokey",
            "value": "a6"
          }
        },
        {
          "type": "element",
          "name": "opcode",
          "attributes": {
            "name": "hikey",
            "value": "a7"
          }
        },
        {
          "type": "element",
          "name": "opcode",
          "attributes": {
            "name": "pitch_keycenter",
            "value": "a#6"
          }
        }
      ]
    },
    {
      "type": "element",
      "name": "group",
      "elements": [
        {
          "type": "element",
          "name": "opcode",
          "attributes": {
            "name": "ampeg_attackcc1",
            "value": "0.5"
          }
        },
        {
          "type": "element",
          "name": "opcode",
          "attributes": {
            "name": "pitch_random",
            "value": "12"
          }
        },
        {
          "type": "element",
          "name": "opcode",
          "attributes": {
            "name": "amp_random",
            "value": "1.5"
          }
        },
        {
          "type": "element",
          "name": "opcode",
          "attributes": {
            "name": "delay_random",
            "value": "0.012"
          }
        },
        {
          "type": "element",
          "name": "opcode",
          "attributes": {
            "name": "ampeg_attack",
            "value": "0.03"
          }
        },
        {
          "type": "element",
          "name": "opcode",
          "attributes": {
            "name": "ampeg_vel2attack",
            "value": "-0.180"
          }
        },
        {
          "type": "element",
          "name": "opcode",
          "attributes": {
            "name": "ampeg_release",
            "value": "1.9"
          }
        },
        {
          "type": "element",
          "name": "opcode",
          "attributes": {
            "name": "ampeg_vel2release",
            "value": "-1.0"
          }
        }
      ]
    },
    {
      "type": "element",
      "name": "region",
      "elements": [
        {
          "type": "element",
          "name": "opcode",
          "attributes": {
            "name": "sample",
            "value": "..\\libs\\SSO\\Samples\\1st Violins\\1st-violins-sus-g3.ogg"
          }
        },
        {
          "type": "element",
          "name": "opcode",
          "attributes": {
            "name": "lokey",
            "value": "g3"
          }
        },
        {
          "type": "element",
          "name": "opcode",
          "attributes": {
            "name": "hikey",
            "value": "g#3"
          }
        },
        {
          "type": "element",
          "name": "opcode",
          "attributes": {
            "name": "pitch_keycenter",
            "value": "g3"
          }
        },
        {
          "type": "element",
          "name": "opcode",
          "attributes": {
            "name": "tune",
            "value": "-10"
          }
        }
      ]
    },
    {
      "type": "element",
      "name": "region",
      "elements": [
        {
          "type": "element",
          "name": "opcode",
          "attributes": {
            "name": "sample",
            "value": "..\\libs\\SSO\\Samples\\1st Violins\\1st-violins-sus-a#3.ogg"
          }
        },
        {
          "type": "element",
          "name": "opcode",
          "attributes": {
            "name": "lokey",
            "value": "a3"
          }
        },
        {
          "type": "element",
          "name": "opcode",
          "attributes": {
            "name": "hikey",
            "value": "b3"
          }
        },
        {
          "type": "element",
          "name": "opcode",
          "attributes": {
            "name": "pitch_keycenter",
            "value": "a#3"
          }
        },
        {
          "type": "element",
          "name": "opcode",
          "attributes": {
            "name": "tune",
            "value": "-5"
          }
        }
      ]
    },
    {
      "type": "element",
      "name": "region",
      "elements": [
        {
          "type": "element",
          "name": "opcode",
          "attributes": {
            "name": "sample",
            "value": "..\\libs\\SSO\\Samples\\1st Violins\\1st-violins-sus-c#4.ogg"
          }
        },
        {
          "type": "element",
          "name": "opcode",
          "attributes": {
            "name": "lokey",
            "value": "c4"
          }
        },
        {
          "type": "element",
          "name": "opcode",
          "attributes": {
            "name": "hikey",
            "value": "d4"
          }
        },
        {
          "type": "element",
          "name": "opcode",
          "attributes": {
            "name": "pitch_keycenter",
            "value": "c#4"
          }
        },
        {
          "type": "element",
          "name": "opcode",
          "attributes": {
            "name": "tune",
            "value": "-5"
          }
        }
      ]
    },
    {
      "type": "element",
      "name": "region",
      "elements": [
        {
          "type": "element",
          "name": "opcode",
          "attributes": {
            "name": "sample",
            "value": "..\\libs\\SSO\\Samples\\1st Violins\\1st-violins-sus-e4.ogg"
          }
        },
        {
          "type": "element",
          "name": "opcode",
          "attributes": {
            "name": "lokey",
            "value": "d#4"
          }
        },
        {
          "type": "element",
          "name": "opcode",
          "attributes": {
            "name": "hikey",
            "value": "f4"
          }
        },
        {
          "type": "element",
          "name": "opcode",
          "attributes": {
            "name": "pitch_keycenter",
            "value": "e4"
          }
        },
        {
          "type": "element",
          "name": "opcode",
          "attributes": {
            "name": "tune",
            "value": "-10"
          }
        }
      ]
    },
    {
      "type": "element",
      "name": "region",
      "elements": [
        {
          "type": "element",
          "name": "opcode",
          "attributes": {
            "name": "sample",
            "value": "..\\libs\\SSO\\Samples\\1st Violins\\1st-violins-sus-g4.ogg"
          }
        },
        {
          "type": "element",
          "name": "opcode",
          "attributes": {
            "name": "lokey",
            "value": "f#4"
          }
        },
        {
          "type": "element",
          "name": "opcode",
          "attributes": {
            "name": "hikey",
            "value": "g#4"
          }
        },
        {
          "type": "element",
          "name": "opcode",
          "attributes": {
            "name": "pitch_keycenter",
            "value": "g4"
          }
        },
        {
          "type": "element",
          "name": "opcode",
          "attributes": {
            "name": "tune",
            "value": "-10"
          }
        }
      ]
    },
    {
      "type": "element",
      "name": "region",
      "elements": [
        {
          "type": "element",
          "name": "opcode",
          "attributes": {
            "name": "sample",
            "value": "..\\libs\\SSO\\Samples\\1st Violins\\1st-violins-sus-a#4.ogg"
          }
        },
        {
          "type": "element",
          "name": "opcode",
          "attributes": {
            "name": "lokey",
            "value": "a4"
          }
        },
        {
          "type": "element",
          "name": "opcode",
          "attributes": {
            "name": "hikey",
            "value": "b4"
          }
        },
        {
          "type": "element",
          "name": "opcode",
          "attributes": {
            "name": "pitch_keycenter",
            "value": "a#4"
          }
        },
        {
          "type": "element",
          "name": "opcode",
          "attributes": {
            "name": "tune",
            "value": "-10"
          }
        }
      ]
    },
    {
      "type": "element",
      "name": "region",
      "elements": [
        {
          "type": "element",
          "name": "opcode",
          "attributes": {
            "name": "sample",
            "value": "..\\libs\\SSO\\Samples\\1st Violins\\1st-violins-sus-c#5.ogg"
          }
        },
        {
          "type": "element",
          "name": "opcode",
          "attributes": {
            "name": "lokey",
            "value": "c5"
          }
        },
        {
          "type": "element",
          "name": "opcode",
          "attributes": {
            "name": "hikey",
            "value": "d5"
          }
        },
        {
          "type": "element",
          "name": "opcode",
          "attributes": {
            "name": "pitch_keycenter",
            "value": "c#5"
          }
        },
        {
          "type": "element",
          "name": "opcode",
          "attributes": {
            "name": "tune",
            "value": "-5"
          }
        }
      ]
    },
    {
      "type": "element",
      "name": "region",
      "elements": [
        {
          "type": "element",
          "name": "opcode",
          "attributes": {
            "name": "sample",
            "value": "..\\libs\\SSO\\Samples\\1st Violins\\1st-violins-sus-e5.ogg"
          }
        },
        {
          "type": "element",
          "name": "opcode",
          "attributes": {
            "name": "lokey",
            "value": "d#5"
          }
        },
        {
          "type": "element",
          "name": "opcode",
          "attributes": {
            "name": "hikey",
            "value": "f5"
          }
        },
        {
          "type": "element",
          "name": "opcode",
          "attributes": {
            "name": "pitch_keycenter",
            "value": "e5"
          }
        },
        {
          "type": "element",
          "name": "opcode",
          "attributes": {
            "name": "tune",
            "value": "-10"
          }
        },
        {
          "type": "element",
          "name": "opcode",
          "attributes": {
            "name": "eq1_freq",
            "value": "102.7"
          }
        },
        {
          "type": "element",
          "name": "opcode",
          "attributes": {
            "name": "eq1_bw",
            "value": "4"
          }
        },
        {
          "type": "element",
          "name": "opcode",
          "attributes": {
            "name": "eq1_gain",
            "value": "-11.4"
          }
        },
        {
          "type": "element",
          "name": "opcode",
          "attributes": {
            "name": "eq2_freq",
            "value": "479.2"
          }
        },
        {
          "type": "element",
          "name": "opcode",
          "attributes": {
            "name": "eq2_bw",
            "value": "1.17"
          }
        },
        {
          "type": "element",
          "name": "opcode",
          "attributes": {
            "name": "eq2_gain",
            "value": "-11.5"
          }
        }
      ]
    },
    {
      "type": "element",
      "name": "region",
      "elements": [
        {
          "type": "element",
          "name": "opcode",
          "attributes": {
            "name": "sample",
            "value": "..\\libs\\SSO\\Samples\\1st Violins\\1st-violins-sus-g5.ogg"
          }
        },
        {
          "type": "element",
          "name": "opcode",
          "attributes": {
            "name": "volume",
            "value": "2"
          }
        },
        {
          "type": "element",
          "name": "opcode",
          "attributes": {
            "name": "lokey",
            "value": "f#5"
          }
        },
        {
          "type": "element",
          "name": "opcode",
          "attributes": {
            "name": "hikey",
            "value": "g#5"
          }
        },
        {
          "type": "element",
          "name": "opcode",
          "attributes": {
            "name": "pitch_keycenter",
            "value": "g5"
          }
        },
        {
          "type": "element",
          "name": "opcode",
          "attributes": {
            "name": "tune",
            "value": "-10"
          }
        },
        {
          "type": "element",
          "name": "opcode",
          "attributes": {
            "name": "eq1_freq",
            "value": "102.7"
          }
        },
        {
          "type": "element",
          "name": "opcode",
          "attributes": {
            "name": "eq1_bw",
            "value": "4"
          }
        },
        {
          "type": "element",
          "name": "opcode",
          "attributes": {
            "name": "eq1_gain",
            "value": "-11.4"
          }
        },
        {
          "type": "element",
          "name": "opcode",
          "attributes": {
            "name": "eq2_freq",
            "value": "479.2"
          }
        },
        {
          "type": "element",
          "name": "opcode",
          "attributes": {
            "name": "eq2_bw",
            "value": "1.17"
          }
        },
        {
          "type": "element",
          "name": "opcode",
          "attributes": {
            "name": "eq2_gain",
            "value": "-11.5"
          }
        }
      ]
    },
    {
      "type": "element",
      "name": "region",
      "elements": [
        {
          "type": "element",
          "name": "opcode",
          "attributes": {
            "name": "sample",
            "value": "..\\libs\\SSO\\Samples\\1st Violins\\1st-violins-sus-a#5.ogg"
          }
        },
        {
          "type": "element",
          "name": "opcode",
          "attributes": {
            "name": "volume",
            "value": "3"
          }
        },
        {
          "type": "element",
          "name": "opcode",
          "attributes": {
            "name": "lokey",
            "value": "a5"
          }
        },
        {
          "type": "element",
          "name": "opcode",
          "attributes": {
            "name": "hikey",
            "value": "b5"
          }
        },
        {
          "type": "element",
          "name": "opcode",
          "attributes": {
            "name": "pitch_keycenter",
            "value": "a#5"
          }
        },
        {
          "type": "element",
          "name": "opcode",
          "attributes": {
            "name": "tune",
            "value": "-10"
          }
        },
        {
          "type": "element",
          "name": "opcode",
          "attributes": {
            "name": "eq1_freq",
            "value": "102.7"
          }
        },
        {
          "type": "element",
          "name": "opcode",
          "attributes": {
            "name": "eq1_bw",
            "value": "4"
          }
        },
        {
          "type": "element",
          "name": "opcode",
          "attributes": {
            "name": "eq1_gain",
            "value": "-11.4"
          }
        },
        {
          "type": "element",
          "name": "opcode",
          "attributes": {
            "name": "eq2_freq",
            "value": "479.2"
          }
        },
        {
          "type": "element",
          "name": "opcode",
          "attributes": {
            "name": "eq2_bw",
            "value": "1.17"
          }
        },
        {
          "type": "element",
          "name": "opcode",
          "attributes": {
            "name": "eq2_gain",
            "value": "-11.5"
          }
        }
      ]
    },
    {
      "type": "element",
      "name": "region",
      "elements": [
        {
          "type": "element",
          "name": "opcode",
          "attributes": {
            "name": "sample",
            "value": "..\\libs\\SSO\\Samples\\1st Violins\\1st-violins-sus-c#6.ogg"
          }
        },
        {
          "type": "element",
          "name": "opcode",
          "attributes": {
            "name": "volume",
            "value": "3"
          }
        },
        {
          "type": "element",
          "name": "opcode",
          "attributes": {
            "name": "lokey",
            "value": "c6"
          }
        },
        {
          "type": "element",
          "name": "opcode",
          "attributes": {
            "name": "hikey",
            "value": "d6"
          }
        },
        {
          "type": "element",
          "name": "opcode",
          "attributes": {
            "name": "pitch_keycenter",
            "value": "c#6"
          }
        },
        {
          "type": "element",
          "name": "opcode",
          "attributes": {
            "name": "tune",
            "value": "-5"
          }
        },
        {
          "type": "element",
          "name": "opcode",
          "attributes": {
            "name": "eq1_freq",
            "value": "102.7"
          }
        },
        {
          "type": "element",
          "name": "opcode",
          "attributes": {
            "name": "eq1_bw",
            "value": "4"
          }
        },
        {
          "type": "element",
          "name": "opcode",
          "attributes": {
            "name": "eq1_gain",
            "value": "-11.4"
          }
        },
        {
          "type": "element",
          "name": "opcode",
          "attributes": {
            "name": "eq2_freq",
            "value": "631.1"
          }
        },
        {
          "type": "element",
          "name": "opcode",
          "attributes": {
            "name": "eq2_bw",
            "value": "2"
          }
        },
        {
          "type": "element",
          "name": "opcode",
          "attributes": {
            "name": "eq2_gain",
            "value": "-11.9"
          }
        }
      ]
    },
    {
      "type": "element",
      "name": "region",
      "elements": [
        {
          "type": "element",
          "name": "opcode",
          "attributes": {
            "name": "sample",
            "value": "..\\libs\\SSO\\Samples\\1st Violins\\1st-violins-sus-e6.ogg"
          }
        },
        {
          "type": "element",
          "name": "opcode",
          "attributes": {
            "name": "volume",
            "value": "2"
          }
        },
        {
          "type": "element",
          "name": "opcode",
          "attributes": {
            "name": "lokey",
            "value": "d#6"
          }
        },
        {
          "type": "element",
          "name": "opcode",
          "attributes": {
            "name": "hikey",
            "value": "f6"
          }
        },
        {
          "type": "element",
          "name": "opcode",
          "attributes": {
            "name": "pitch_keycenter",
            "value": "e6"
          }
        },
        {
          "type": "element",
          "name": "opcode",
          "attributes": {
            "name": "tune",
            "value": "-15"
          }
        },
        {
          "type": "element",
          "name": "opcode",
          "attributes": {
            "name": "eq1_freq",
            "value": "102.7"
          }
        },
        {
          "type": "element",
          "name": "opcode",
          "attributes": {
            "name": "eq1_bw",
            "value": "4"
          }
        },
        {
          "type": "element",
          "name": "opcode",
          "attributes": {
            "name": "eq1_gain",
            "value": "-11.4"
          }
        },
        {
          "type": "element",
          "name": "opcode",
          "attributes": {
            "name": "eq2_freq",
            "value": "631.1"
          }
        },
        {
          "type": "element",
          "name": "opcode",
          "attributes": {
            "name": "eq2_bw",
            "value": "2"
          }
        },
        {
          "type": "element",
          "name": "opcode",
          "attributes": {
            "name": "eq2_gain",
            "value": "-11.9"
          }
        }
      ]
    },
    {
      "type": "element",
      "name": "region",
      "elements": [
        {
          "type": "element",
          "name": "opcode",
          "attributes": {
            "name": "sample",
            "value": "..\\libs\\SSO\\Samples\\1st Violins\\1st-violins-sus-g6.ogg"
          }
        },
        {
          "type": "element",
          "name": "opcode",
          "attributes": {
            "name": "volume",
            "value": "2"
          }
        },
        {
          "type": "element",
          "name": "opcode",
          "attributes": {
            "name": "lokey",
            "value": "f#6"
          }
        },
        {
          "type": "element",
          "name": "opcode",
          "attributes": {
            "name": "hikey",
            "value": "g#6"
          }
        },
        {
          "type": "element",
          "name": "opcode",
          "attributes": {
            "name": "pitch_keycenter",
            "value": "g6"
          }
        },
        {
          "type": "element",
          "name": "opcode",
          "attributes": {
            "name": "tune",
            "value": "-10"
          }
        },
        {
          "type": "element",
          "name": "opcode",
          "attributes": {
            "name": "eq1_freq",
            "value": "102.7"
          }
        },
        {
          "type": "element",
          "name": "opcode",
          "attributes": {
            "name": "eq1_bw",
            "value": "4"
          }
        },
        {
          "type": "element",
          "name": "opcode",
          "attributes": {
            "name": "eq1_gain",
            "value": "-11.4"
          }
        },
        {
          "type": "element",
          "name": "opcode",
          "attributes": {
            "name": "eq2_freq",
            "value": "631.1"
          }
        },
        {
          "type": "element",
          "name": "opcode",
          "attributes": {
            "name": "eq2_bw",
            "value": "2"
          }
        },
        {
          "type": "element",
          "name": "opcode",
          "attributes": {
            "name": "eq2_gain",
            "value": "-11.9"
          }
        }
      ]
    },
    {
      "type": "element",
      "name": "region",
      "elements": [
        {
          "type": "element",
          "name": "opcode",
          "attributes": {
            "name": "sample",
            "value": "..\\libs\\SSO\\Samples\\1st Violins\\1st-violins-sus-a#6.ogg"
          }
        },
        {
          "type": "element",
          "name": "opcode",
          "attributes": {
            "name": "volume",
            "value": "1"
          }
        },
        {
          "type": "element",
          "name": "opcode",
          "attributes": {
            "name": "lokey",
            "value": "a6"
          }
        },
        {
          "type": "element",
          "name": "opcode",
          "attributes": {
            "name": "hikey",
            "value": "a7"
          }
        },
        {
          "type": "element",
          "name": "opcode",
          "attributes": {
            "name": "pitch_keycenter",
            "value": "a#6"
          }
        },
        {
          "type": "element",
          "name": "opcode",
          "attributes": {
            "name": "tune",
            "value": "-10"
          }
        },
        {
          "type": "element",
          "name": "opcode",
          "attributes": {
            "name": "eq1_freq",
            "value": "102.7"
          }
        },
        {
          "type": "element",
          "name": "opcode",
          "attributes": {
            "name": "eq1_bw",
            "value": "4"
          }
        },
        {
          "type": "element",
          "name": "opcode",
          "attributes": {
            "name": "eq1_gain",
            "value": "-11.4"
          }
        },
        {
          "type": "element",
          "name": "opcode",
          "attributes": {
            "name": "eq2_freq",
            "value": "631.1"
          }
        },
        {
          "type": "element",
          "name": "opcode",
          "attributes": {
            "name": "eq2_bw",
            "value": "2"
          }
        },
        {
          "type": "element",
          "name": "opcode",
          "attributes": {
            "name": "eq2_gain",
            "value": "-11.9"
          }
        }
      ]
    }
  ]
}